tweetscrape/__init__.py
tweetscrape/conversation_tweets.py
tweetscrape/profile_tweets.py
tweetscrape/search_tweets.py
tweetscrape/tweets_scrape.py
tweetscrape/twitter_scrape.py
tweetscrape/users_scrape.py
tweetscrape/model/__init__.py
tweetscrape/model/tweet_model.py
tweetscrape/model/user_model.py
tweetscrape-0.6.2.dist-info/AUTHORS.rst
tweetscrape-0.6.2.dist-info/LICENSE.txt
tweetscrape-0.6.2.dist-info/METADATA
tweetscrape-0.6.2.dist-info/WHEEL
tweetscrape-0.6.2.dist-info/top_level.txt
tweetscrape-0.6.2.dist-info/RECORD
