Metadata-Version: 2.1
Name: tweetscrape
Version: 0.6.2
Summary: Scrape the Twitter frontend API without any authentication and restriction.
Home-page: https://github.com/5hirish/tweet_scrapper
Author: Shirish Kadam
Author-email: shirishkadam35@gmail.com
License: gpl3
Platform: UNKNOWN
Classifier: Development Status :: 5 - Production/Stable
Classifier: Intended Audience :: Education
Classifier: Intended Audience :: Developers
Classifier: Intended Audience :: Science/Research
Classifier: Operating System :: OS Independent
Classifier: License :: OSI Approved :: GNU General Public License v3 (GPLv3)
Classifier: Programming Language :: Python
Classifier: Programming Language :: Python :: 3
Classifier: Programming Language :: Python :: 3.5
Classifier: Programming Language :: Python :: 3.6
Classifier: Topic :: Software Development :: Libraries :: Python Modules
Classifier: Topic :: Scientific/Engineering
Classifier: Topic :: Scientific/Engineering :: Information Analysis
Requires-Python: >=3.5.*
Requires-Dist: lxml
Requires-Dist: requests
